remote_sensors
