Metadata-Version: 2.1
Name: remote-sensors
Version: 0.1b1
Summary: Remote Sensors API framework
Home-page: https://bitbucket.org/kiotsystem/remote-sensors-api
Author: Arnulfo Solis
Author-email: arnulfojr94@gmail.com
License: UNKNOWN
Download-URL: https://bitbucket.org/kiotsystem/remote-sensors-api/get/0.1b1.tar.gz
Keywords: iot,embedded,remote_sensors,arduino,sensors,xbee
Platform: any
Classifier: Intended Audience :: Developers
Classifier: License :: OSI Approved :: MIT License
Classifier: Operating System :: OS Independent
Classifier: Programming Language :: Python
Classifier: Programming Language :: Python :: 3
Classifier: Programming Language :: Python :: 3.7
Classifier: Programming Language :: Python :: Implementation :: CPython
Classifier: Programming Language :: Python :: Implementation :: PyPy
Classifier: Topic :: Software Development :: Libraries :: Python Modules
